{"Greg Shaw - Worlds Day 2 - DS ISB": {"userinfo": {"fullname": "Greg Shaw", "event": "Worlds Day 2", "deckside": "DS", "deckname": "ISB"}, "deckinfo": {"username": "ShawDay2", "deckside": "DS", "deckname": "ISB"}, "STARTING": ["Knowledge And Defense (V)", "ISB Operations", "Coruscant", "Prepared Defenses", "Imperial Arrest Order", "Kuat Drive Yards (V)", "Silence Is Golden (V)"], "CHARACTERS": ["4-LOM With Concussion Rifle (V)", "4-LOM With Concussion Rifle (V)", "5D6-RA-7 (Fivedesix) (V)", "5D6-RA-7 (Fivedesix) (V)", "5D6-RA-7 (Fivedesix) (V)", "5D6-RA-7 (Fivedesix) (V)", "Admiral Chiraneau", "Admiral Ozzel", "Agent Kallus", "Agent Kallus", "Captain Gilad Pellaeon", "Captain Godherdt", "Colonel Wullf Yularen (V)", "Colonel Wullf Yularen (V)", "Corporal Vandolay (V)", "Darth Vader, Emperor's Enforcer", "Grand Admiral Thrawn", "Guri", "Lt. Pol Treidum (V)", "Officer Evax", "Tarkin (V)", "Tarkin (V)", "U-3PO (Yoo-Threepio)", "U-3PO (Yoo-Threepio)"], "EFFECTS": ["Forced Servitude", "Forced Servitude", "Lateral Damage", "Tarkin's Bounty (V)", "There'll Be Hell To Pay"], "INTERRUPTS": ["Cold Feet (V)", "Control & Set For Stun", "Death Squadron Assignment", "Force Push (V)", "I Can't Shake Him! (V)", "Imbalance & Kintan Strider", "Imbalance & Kintan Strider", "Imperial Code Cylinder (V)", "Imperial Code Cylinder (V)", "Imperial Command", "Imperial Command", "Imperial Command", "Voyeur"], "LOCATIONS": ["Coruscant: Imperial Square", "Death Star II: Docking Bay", "Executor: Docking Bay", "Jabba's Palace: Droid Workshop", "Kashyyyk", "Mustafar", "Mustafar: Vader's Castle"], "STARSHIPS": ["Avenger", "Stalker (V)", "Tyrant", "Vengeance (V)"]}}