{"Tom Kelly - Worlds Day 1 - DS IE": {"userinfo": {"fullname": "Tom Kelly", "event": "Worlds Day 1", "deckside": "DS", "deckname": "IE"}, "deckinfo": {"username": "TKelly", "deckside": "DS", "deckname": "IE"}, "STARTING": ["Knowledge And Defense (V)", "Imperial Entanglements", "Tatooine (V)", "Devastator", "Tatooine: Mos Espa", "Prepared Defenses", "Endor Shield (V)", "Imperial Arrest Order", "Mobilization Points", "ADMIRAL'S ORDERS", "Battle Deployment", "We're In Attack Position Now"], "CHARACTERS": ["Admiral Motti (V)", "Admiral Ozzel", "Admiral Piett", "Colonel Wullf Yularen (V)", "Commander Desanne", "Corporal Drelosyn", "DS-61-5", "Darth Vader (V)", "Emperor Palpatine", "General Veers (V)", "Grand Admiral Thrawn", "Grand Moff Tarkin (V)", "Maarek Stele, The Emperor's Reach", "Mara Jade With Lightsaber", "Moff Gideon", "Sergeant Barich", "Sergeant Elsek", "Sergeant Irol", "Stormtrooper Garrison"], "EFFECTS": ["Imperial Decree (V)", "Imperial Enforcement", "Imperial Justice (V)", "Something Special Planned For Them (V)", "Tarkin's Bounty (V)", "Tatooine Occupation", "Tatooine Occupation", "Tatooine Occupation"], "INTERRUPTS": ["A Dark Time For The Rebellion (V)", "A Dark Time For The Rebellion (V)", "Force Push (V)", "I Can't Shake Him! (V)", "I Can't Shake Him! (V)", "Imperial Barrier", "Imperial Command", "Imperial Command", "Imperial Command", "Tarkin's Orders", "Trample"], "LOCATIONS": ["Executor: Docking Bay", "Tatooine: Desert Heart", "Tatooine: Mos Espa Docking Bay", "Tatooine: Watto's Junkyard"], "STARSHIPS": ["Emperor's Personal Shuttle", "Flagship Executor"], "VEHICLES": ["Blizzard 2 (V)", "Blizzard 4", "Blizzard Scout 1 (V)", "Tempest 1", "Tempest Scout 1"]}}